geomlcv/__init__.py
geomlcv/src/run_predict.py
geomlcv/src/run_sentinel_ndwi_mask.py
geomlcv/utils/bash_scripts/delete_s3_files.sh
geomlcv/utils/download_data/__init__.py
geomlcv/utils/download_data/aws.py
geomlcv/utils/download_data/google.py
geomlcv/utils/download_data/multiprocess.py
geomlcv/utils/download_data/planetary_computer.py
geomlcv/utils/download_data/utils.py
geomlcv/utils/nn.py
geomlcv/utils/process_images/__init__.py
geomlcv/utils/process_images/ndwi.py
geomlcv/utils/process_images/utils.py
geomlcv-0.0.14.dist-info/METADATA
geomlcv-0.0.14.dist-info/WHEEL
geomlcv-0.0.14.dist-info/RECORD
