Metadata-Version: 2.1
Name: geomlcv
Version: 0.0.14
Summary: CV workflow helpers.
Home-page: https://github.com/pgzmnk/geomlcv
License: MIT
Author: pgzmnk
Author-email: pgzmnk@gmail.com
Maintainer: pgzmnk
Maintainer-email: pgzmnk@gmail.com
Requires-Python: >=3.8,<4.0
Classifier: License :: OSI Approved :: MIT License
Classifier: Programming Language :: Python :: 3
Classifier: Programming Language :: Python :: 3.8
Classifier: Programming Language :: Python :: 3.9
Classifier: Programming Language :: Python :: 3.10
Classifier: Programming Language :: Python :: 3.11
Provides-Extra: google
Requires-Dist: boto3 (>=1.33.10,<2.0.0)
Requires-Dist: click (>=8.1.7,<9.0.0)
Requires-Dist: duckdb (>=0.8.1)
Requires-Dist: ensemble-boxes (>=1.0.9,<2.0.0)
Requires-Dist: geopandas (>=0.10.1,<0.11.0)
Requires-Dist: googlemaps (>=4.10.0,<5.0.0) ; extra == "google"
Requires-Dist: loguru (>=0.7.2,<0.8.0)
Requires-Dist: opencv-python (>=4.8.1.78,<5.0.0.0)
Requires-Dist: pyarrow (>=14.0.2,<15.0.0)
Requires-Dist: python-dotenv (>=1.0.0,<2.0.0)
Requires-Dist: roboflow (>=1.1.12,<2.0.0)
Requires-Dist: s3fs (>=2023.12.2,<2024.0.0)
Requires-Dist: scikit-image (==0.19.3)
Requires-Dist: scikit-learn (>=1.3.2,<2.0.0)
Requires-Dist: torch (>=2.1.1,<3.0.0)
Requires-Dist: torchvision (>=0.16.1,<0.17.0)
Project-URL: Repository, https://github.com/pgzmnk/geomlcv
